flask_container/__init__.py
flask_container/db.py
flask_container/schema.sql
flask_container/api/__init__.py
flask_container/apps/__init__.py
flask_container/apps/apps.json
flask_container/static/style.css
flask_container/static/swagger.json
flask_container/templates/base.html
flask_container/templates/auth/login.html
flask_container/templates/auth/register.html
tests/__init__.py
tests/conftest.py
tests/test_auth.py
tests/test_blog.py
tests/test_db.py
tests/test_factory.py
flask_container-1.0.5.dist-info/LICENSE
flask_container-1.0.5.dist-info/METADATA
flask_container-1.0.5.dist-info/WHEEL
flask_container-1.0.5.dist-info/top_level.txt
flask_container-1.0.5.dist-info/RECORD
