Metadata-Version: 2.1
Name: flask-container
Version: 1.0.5
Summary: A small example package
Home-page: https://github.com/JoseRoberts87/flask_container
Author: Jose Roberts
Author-email: Jose.Roberts@intracitygeeks.org
License: MIT
Platform: UNKNOWN
Classifier: License :: OSI Approved :: MIT License
Classifier: Programming Language :: Python :: 3
Classifier: Programming Language :: Python :: 3.6
Requires-Python: >=3.6
Requires-Dist: flask
Requires-Dist: Flask-RESTful (==0.3.7)
Requires-Dist: flask-swagger-ui (==3.20.9)
